bucketbrigade/.DS_Store
bucketbrigade/__init__.py
bucketbrigade/aws.py
bucketbrigade/core.py
bucketbrigade/tests/test_aws.py
bucketbrigade/tests/test_core.py
bucketbrigade-0.0.1.dist-info/LICENSE
bucketbrigade-0.0.1.dist-info/METADATA
bucketbrigade-0.0.1.dist-info/WHEEL
bucketbrigade-0.0.1.dist-info/RECORD
