Metadata-Version: 2.1
Name: bucketbrigade
Version: 0.0.1
Summary: 
Author: Doug Hudgeon
Author-email: doug.hudgeon@managedfunctions.com
Requires-Python: >=3.11,<4.0
Classifier: Programming Language :: Python :: 3
Classifier: Programming Language :: Python :: 3.11
Requires-Dist: arrow (>=1.3.0,<2.0.0)
Requires-Dist: boto3
Requires-Dist: botocore
Requires-Dist: modal (>=0.56.4590,<0.57.0)
Requires-Dist: pandas (>=2.1.4,<3.0.0)
Requires-Dist: pydantic (>=2.3.0,<3.0.0)
Requires-Dist: s3fs[boto3] (>=2023.12.0)
